penguinstransittoolbox/__init__.py
penguinstransittoolbox/gis.py
penguinstransittoolbox/zip.py
penguinstransittoolbox-0.1.2.dist-info/licenses/LICENSE
penguinstransittoolbox-0.1.2.dist-info/METADATA
penguinstransittoolbox-0.1.2.dist-info/WHEEL
penguinstransittoolbox-0.1.2.dist-info/top_level.txt
penguinstransittoolbox-0.1.2.dist-info/RECORD
