Metadata-Version: 2.4
Name: penguinstransittoolbox
Version: 0.1.2
Summary: Penguin's Transit Toolbox :  a simple python toolbox for managing GTFS data. Work in progress
Author-email: Maxence Marchand <mxnc.marchand@gmail.com>
License: Unlicense
Project-URL: Homepage, https://github.com/mxncmrchnd/penguinstransittoolbox
Project-URL: Repository, https://github.com/mxncmrchnd/penguinstransittoolbox
Project-URL: Issues, https://github.com/mxncmrchnd/penguinstransittoolbox/issues
Keywords: GTFS,geopandas,transit,transport,shapely,data
Requires-Python: >=3.9
License-File: LICENSE
Requires-Dist: pandas>=1.5
Requires-Dist: geopandas>=0.13
Requires-Dist: shapely>=2.0
Requires-Dist: requests>=2.30
Requires-Dist: fiona>=1.9
Requires-Dist: pyproj>=3.5
Provides-Extra: dev
Requires-Dist: pytest>=7.0; extra == "dev"
Requires-Dist: ruff>=0.4; extra == "dev"
Requires-Dist: black>=24.0; extra == "dev"
Requires-Dist: mypy>=1.0; extra == "dev"
Dynamic: license-file
